talbot/__init__.py
talbot/author_utils.py
talbot/base_utils.py
talbot/constants.py
talbot/date_utils.py
talbot/doi_utils.py
talbot/metadata/__init__.py
talbot/metadata/metadata.py
talbot/readers/__init__.py
talbot/readers/citeproc_reader.py
talbot/readers/codemeta_reader.py
talbot/readers/crossref_reader.py
talbot/readers/datacite_reader.py
talbot/readers/ris_reader.py
talbot/readers/schema_org_reader.py
talbot/resources/schemas/datacite-v4.3.json
talbot/resources/schemas/talbot.json
talbot/resources/spdx/licenses.json
talbot/utils.py
talbot/version.py
talbot/writers/__init__.py
talbot/writers/bibtex_writer.py
talbot/writers/citation_writer.py
talbot/writers/citeproc_writer.py
talbot/writers/datacite_writer.py
talbot/writers/ris_writer.py
talbot/writers/schema_org_writer.py
talbot-0.5.1.dist-info/LICENSE
talbot-0.5.1.dist-info/WHEEL
talbot-0.5.1.dist-info/METADATA
talbot-0.5.1.dist-info/RECORD
