Metadata-Version: 2.1
Name: talbot
Version: 0.5.1
Summary: Library for conversions of scholarly metadata
Author: Martin Fenner
Author-email: martin@front-matter.io
Requires-Python: >=3.7.1,<4.0.0
Classifier: Programming Language :: Python :: 3
Classifier: Programming Language :: Python :: 3.8
Classifier: Programming Language :: Python :: 3.9
Classifier: Programming Language :: Python :: 3.10
Classifier: Programming Language :: Python :: 3.11
Requires-Dist: PyYAML (>=6.0,<7.0)
Requires-Dist: beautifulsoup4 (>=4.11,<5.0)
Requires-Dist: bibtexparser (>=1.4,<2.0)
Requires-Dist: bleach (>=6.0,<7.0)
Requires-Dist: citeproc-py (>=0.6,<0.7)
Requires-Dist: citeproc-py-styles (>0.1)
Requires-Dist: codecov (>=2.1,<3.0)
Requires-Dist: datacite (>=1.1,<2.0)
Requires-Dist: dateparser (>=1.1.7,<2.0.0)
Requires-Dist: docutils (>=0.19,<0.20)
Requires-Dist: jsonschema (>=4.17,<5.0)
Requires-Dist: lxml (>=4.9,<5.0)
Requires-Dist: mkdocs (>=1.4,<2.0)
Requires-Dist: mkdocs-jupyter (>=0.22,<0.23)
Requires-Dist: mkdocs-material (>=8.0,<9.0)
Requires-Dist: mkdocs-material-extensions (>=1.1,<2.0)
Requires-Dist: pydash (>=6.0,<7.0)
Requires-Dist: pytest (>=7.2,<8.0)
Requires-Dist: pytest-cov (>=4.0,<5.0)
Requires-Dist: pytest-recording (>=0.12,<0.13)
Requires-Dist: requests (>=2.28,<3.0)
Requires-Dist: simplejson (>=3.18,<4.0)
Requires-Dist: sphinx-autodoc-typehints (>=1.19,<2.0)
Requires-Dist: sphinxcontrib-issuetracker (>=0.11,<0.12)
Requires-Dist: tqdm (>=4.64,<5.0)
Requires-Dist: types-beautifulsoup4 (>=4.11,<5.0)
Requires-Dist: types-bleach (>=6.0,<7.0)
Requires-Dist: types-dateparser (>=1.1,<2.0)
Requires-Dist: types-requests (>=2.28,<3.0)
Requires-Dist: vcrpy (>=4.2,<5.0)
